lambda_deployer/__init__.py
lambda_deployer/cli.py
lambda_deployer/lambda_deployer.py
yald/__init__.py
yald/cli.py
yald/yald.py
yald-0.2.1.dist-info/AUTHORS.rst
yald-0.2.1.dist-info/LICENSE
yald-0.2.1.dist-info/METADATA
yald-0.2.1.dist-info/WHEEL
yald-0.2.1.dist-info/entry_points.txt
yald-0.2.1.dist-info/top_level.txt
yald-0.2.1.dist-info/zip-safe
yald-0.2.1.dist-info/RECORD
