Metadata-Version: 2.1
Name: yald
Version: 0.2.1
Summary: Simple script for deploying code for a Lambda.
Home-page: https://github.com/seanlynch/yald
Author: Sean Lynch
Author-email: seanl@literati.org
License: Apache Software License 2.0
Keywords: yald
Platform: UNKNOWN
Classifier: Development Status :: 2 - Pre-Alpha
Classifier: Intended Audience :: Developers
Classifier: License :: OSI Approved :: Apache Software License
Classifier: Natural Language :: English
Classifier: Programming Language :: Python :: 3
Classifier: Programming Language :: Python :: 3.5
Classifier: Programming Language :: Python :: 3.6
Classifier: Programming Language :: Python :: 3.7
Classifier: Programming Language :: Python :: 3.8
Requires-Python: >=3.8
Requires-Dist: boto3
